__init__.py
buildpack.py
main.py
brilliant_PaaS_buildpack-0.2.0.dist-info/METADATA
brilliant_PaaS_buildpack-0.2.0.dist-info/WHEEL
brilliant_PaaS_buildpack-0.2.0.dist-info/top_level.txt
brilliant_PaaS_buildpack-0.2.0.dist-info/RECORD
